elasticsearch_sbs/__init__.py
elasticsearch_sbs/custom_exceptions.py
elasticsearch_sbs-2.0.0.dist-info/LICENCE
elasticsearch_sbs-2.0.0.dist-info/METADATA
elasticsearch_sbs-2.0.0.dist-info/WHEEL
elasticsearch_sbs-2.0.0.dist-info/top_level.txt
elasticsearch_sbs-2.0.0.dist-info/RECORD
