Metadata-Version: 2.1
Name: elasticsearch-sbs
Version: 2.0.0
Summary: A package for ElasticSearch operations.
Home-page: UNKNOWN
Author: Sara Ben Shabbat
Author-email: sarabenshabbat@gmail.com
License: UNKNOWN
Platform: UNKNOWN
Classifier: Programming Language :: Python :: 3
Classifier: License :: OSI Approved :: MIT License
Classifier: Operating System :: OS Independent
Requires-Python: >=3.6
